camels_library.py
CAMELS_library-0.4.dist-info/LICENSE
CAMELS_library-0.4.dist-info/METADATA
CAMELS_library-0.4.dist-info/WHEEL
CAMELS_library-0.4.dist-info/top_level.txt
CAMELS_library-0.4.dist-info/RECORD
