Metadata-Version: 2.1
Name: CAMELS-library
Version: 0.4
Summary: Python routines to analyze the data from the simulations of the Cosmology and Astrophysics with MachinE Learning Simulations (CAMELS) project
Home-page: https://github.com/franciscovillaescusa/CAMELS
Author: Francisco Villaescusa-Navarro
Author-email: villaescusa.francisco@gmail.com
License: MIT
Platform: UNKNOWN
License-File: LICENSE
Requires-Dist: scipy
Requires-Dist: h5py
Requires-Dist: Pylians
Requires-Dist: tables
